x3dh/__init__.py
x3dh/base_state.py
x3dh/crypto_provider.py
x3dh/crypto_provider_cryptography.py
x3dh/identity_key_pair.py
x3dh/migrations.py
x3dh/models.py
x3dh/pre_key_pair.py
x3dh/py.typed
x3dh/signed_pre_key_pair.py
x3dh/state.py
x3dh/types.py
x3dh/version.py
x3dh-1.3.0.dist-info/licenses/LICENSE
x3dh-1.3.0.dist-info/METADATA
x3dh-1.3.0.dist-info/WHEEL
x3dh-1.3.0.dist-info/top_level.txt
x3dh-1.3.0.dist-info/RECORD
