Metadata-Version: 2.4
Name: X3DH
Version: 1.3.0
Summary: A Python implementation of the Extended Triple Diffie-Hellman key agreement protocol.
Author-email: "Tim Henkes (Syndace)" <me@syndace.dev>
Maintainer-email: "Tim Henkes (Syndace)" <me@syndace.dev>
License-Expression: MIT
Project-URL: Documentation, https://python-x3dh.readthedocs.io/
Project-URL: Repository, https://github.com/Syndace/python-x3dh
Project-URL: Issues, https://github.com/Syndace/python-x3dh/issues
Project-URL: Changelog, https://github.com/Syndace/python-x3dh/blob/main/CHANGELOG.md
Classifier: Development Status :: 5 - Production/Stable
Classifier: Programming Language :: Python :: 3
Classifier: Programming Language :: Python :: 3 :: Only
Classifier: Programming Language :: Python :: 3.10
Classifier: Programming Language :: Python :: 3.11
Classifier: Programming Language :: Python :: 3.12
Classifier: Programming Language :: Python :: 3.13
Classifier: Programming Language :: Python :: 3.14
Classifier: Programming Language :: Python :: Implementation :: CPython
Classifier: Programming Language :: Python :: Implementation :: PyPy
Classifier: Intended Audience :: Developers
Classifier: Topic :: Security :: Cryptography
Requires-Python: >=3.10
License-File: LICENSE
Requires-Dist: XEdDSA<2,>=1.0.0
Requires-Dist: cryptography>=3.3.2
Requires-Dist: pydantic>=1.7.4
Requires-Dist: typing-extensions>=4.3.0
Provides-Extra: docs
Requires-Dist: sphinx; extra == "docs"
Requires-Dist: sphinx-rtd-theme; extra == "docs"
Requires-Dist: sphinx-autodoc-typehints; extra == "docs"
Provides-Extra: test
Requires-Dist: pytest; extra == "test"
Requires-Dist: pytest-asyncio; extra == "test"
Requires-Dist: pytest-cov; extra == "test"
Provides-Extra: lint
Requires-Dist: mypy; extra == "lint"
Requires-Dist: pylint; extra == "lint"
Requires-Dist: flake8; extra == "lint"
Requires-Dist: flake8-pyproject; extra == "lint"
Provides-Extra: dev
Requires-Dist: x3dh[docs,lint,test]; extra == "dev"
Dynamic: license-file
